Metadata-Version: 2.1
Name: qzecs
Version: 0.0.1
Summary: zerodata
Home-page: 
Author: SIR
Author-email: sr.pentesters@gmail.com
License: MIT
Keywords: qzecs
Classifier: Development Status :: 5 - Production/Stable
Classifier: Intended Audience :: Education
Classifier: Operating System :: Microsoft :: Windows :: Windows 10
Classifier: License :: OSI Approved :: MIT License
Classifier: Programming Language :: Python :: 3
License-File: LICENCE.txt
